googolplex/__init__.py
googolplex/test.py
googolplex-0.5.dist-info/LICENSE
googolplex-0.5.dist-info/METADATA
googolplex-0.5.dist-info/WHEEL
googolplex-0.5.dist-info/top_level.txt
googolplex-0.5.dist-info/RECORD
